[
    {
        "group_name": "静岡メロン生産者の会",
        "item_name": "メロン",
        "distribution_manager": "△△会社 飯田純一/■■会社 三田次郎…",
        "grading_person": "○○小売店/北村太郎"
    },
    {
        "group_name": "富士トマトグループ",
        "item_name": "トマト",
        "distribution_manager": "△△会社/飯田純一",
        "grading_person": "○○小売店/北村太郎"
    },
    {
        "group_name": "静岡メロン生産者の会",
        "item_name": "メロン",
        "distribution_manager": "△△会社 飯田純一/■■会社 三田次郎…",
        "grading_person": "○○小売店/北村太郎"
    },
    {
        "group_name": "富士トマトグループ",
        "item_name": "トマト",
        "distribution_manager": "△△会社/飯田純一",
        "grading_person": "○○小売店/北村太郎"
    },
    {
        "group_name": "静岡メロン生産者の会",
        "item_name": "メロン",
        "distribution_manager": "△△会社 飯田純一/■■会社 三田次郎…",
        "grading_person": "○○小売店/北村太郎"
    },
    {
        "group_name": "富士トマトグループ",
        "item_name": "トマト",
        "distribution_manager": "△△会社/飯田純一",
        "grading_person": "○○小売店/北村太郎"
    },
    {
        "group_name": "静岡メロン生産者の会",
        "item_name": "メロン",
        "distribution_manager": "△△会社 飯田純一/■■会社 三田次郎…",
        "grading_person": "○○小売店/北村太郎"
    },
    {
        "group_name": "富士トマトグループ",
        "item_name": "トマト",
        "distribution_manager": "△△会社/飯田純一",
        "grading_person": "○○小売店/北村太郎"
    },
    {
        "group_name": "静岡メロン生産者の会",
        "item_name": "メロン",
        "distribution_manager": "△△会社 飯田純一/■■会社 三田次郎…",
        "grading_person": "○○小売店/北村太郎"
    },
    {
        "group_name": "富士トマトグループ",
        "item_name": "トマト",
        "distribution_manager": "△△会社/飯田純一",
        "grading_person": "○○小売店/北村太郎"
    }
]
